pycalil/__init__.py
pycalil/pycalil.py
pycalil-1.4.dist-info/METADATA
pycalil-1.4.dist-info/WHEEL
pycalil-1.4.dist-info/top_level.txt
pycalil-1.4.dist-info/RECORD
