Metadata-Version: 2.1
Name: pycalil
Version: 1.4
Summary: A package that enables the Calil Library API to be used from Python.
Home-page: https://github.com/warada0209/pycalil
Author: warada0209
Author-email: warada0209@gmail.com
License: UNKNOWN
Platform: UNKNOWN
Classifier: Programming Language :: Python :: 3.9
Classifier: License :: OSI Approved :: MIT License
Classifier: Operating System :: OS Independent
